robot_kinematics/__init__.py
robot_kinematics/core/base.py
robot_kinematics/core/exceptions.py
robot_kinematics/core/jacobian.py
robot_kinematics/core/transforms.py
robot_kinematics/forward/dh_kinematics.py
robot_kinematics/forward/urdf_kinematics.py
robot_kinematics/integration/pybullet_utils.py
robot_kinematics/integration/urdf_utils.py
robot_kinematics/inverse/analytical.py
robot_kinematics/inverse/hybrid.py
robot_kinematics/inverse/numerical.py
robot_kinematics/robots/mobile.py
robot_kinematics/robots/parallel.py
robot_kinematics/robots/serial.py
robot_kinematics/utils/performance.py
robot_kinematics/utils/singularity.py
robot_kinematics/utils/workspace.py
robot_kinematics-1.1.0.dist-info/licenses/LICENSE
tests/__init__.py
tests/test_all.py
tests/test_core.py
tests/test_forward.py
tests/test_inverse.py
tests/test_robots.py
tests/test_utils.py
robot_kinematics-1.1.0.dist-info/METADATA
robot_kinematics-1.1.0.dist-info/WHEEL
robot_kinematics-1.1.0.dist-info/top_level.txt
robot_kinematics-1.1.0.dist-info/RECORD
