Metadata-Version: 2.4
Name: robot_kinematics
Version: 1.1.0
Summary: A comprehensive robotics kinematics library with URDF and PyBullet integration
Home-page: https://github.com/Sherin-SEF-AI/robo-kinematics
Author: Sherin Joseph Roy
Author-email: sherin.joseph2217@gmail.com
Project-URL: Bug Reports, https://github.com/Sherin-SEF-AI/robo-kinematics/issues
Project-URL: Source, https://github.com/Sherin-SEF-AI/robo-kinematics
Project-URL: Documentation, https://robotkinematics.readthedocs.io/
Keywords: robotics,kinematics,forward-kinematics,inverse-kinematics,jacobian,urdf,pybullet
Classifier: Development Status :: 4 - Beta
Classifier: Intended Audience :: Science/Research
Classifier: License :: OSI Approved :: MIT License
Classifier: Operating System :: OS Independent
Classifier: Programming Language :: Python :: 3
Classifier: Programming Language :: Python :: 3.8
Classifier: Programming Language :: Python :: 3.9
Classifier: Programming Language :: Python :: 3.10
Classifier: Programming Language :: Python :: 3.11
Classifier: Programming Language :: Python :: 3.12
Classifier: Topic :: Scientific/Engineering :: Artificial Intelligence
Classifier: Topic :: Software Development :: Libraries :: Python Modules
Requires-Python: >=3.8
License-File: LICENSE
Requires-Dist: numpy>=1.21.0
Requires-Dist: scipy>=1.7.0
Requires-Dist: matplotlib>=3.5.0
Requires-Dist: pytest>=6.0.0
Requires-Dist: pytest-cov>=2.12.0
Requires-Dist: numba>=0.56.0
Requires-Dist: lxml>=4.6.0
Requires-Dist: xmltodict>=0.12.0
Requires-Dist: pybullet
Provides-Extra: dev
Requires-Dist: pytest>=6.0.0; extra == "dev"
Requires-Dist: pytest-cov>=2.12.0; extra == "dev"
Requires-Dist: black>=22.0.0; extra == "dev"
Requires-Dist: flake8>=4.0.0; extra == "dev"
Requires-Dist: mypy>=0.950; extra == "dev"
Provides-Extra: docs
Requires-Dist: sphinx>=4.0.0; extra == "docs"
Requires-Dist: sphinx-rtd-theme>=1.0.0; extra == "docs"
Requires-Dist: nbsphinx>=0.8.0; extra == "docs"
Provides-Extra: visualization
Requires-Dist: pybullet>=3.2.0; extra == "visualization"
Requires-Dist: matplotlib>=3.5.0; extra == "visualization"
Provides-Extra: full
Requires-Dist: pybullet>=3.2.0; extra == "full"
Requires-Dist: matplotlib>=3.5.0; extra == "full"
Requires-Dist: scipy>=1.8.0; extra == "full"
Requires-Dist: lxml>=4.6.0; extra == "full"
Requires-Dist: xmltodict>=0.12.0; extra == "full"
Dynamic: author
Dynamic: author-email
Dynamic: classifier
Dynamic: description
Dynamic: description-content-type
Dynamic: home-page
Dynamic: keywords
Dynamic: license-file
Dynamic: project-url
Dynamic: provides-extra
Dynamic: requires-dist
Dynamic: requires-python
Dynamic: summary
